LATSourceModel/SourceList.py
LATSourceModel/__init__.py
LATSourceModel/make4FGLxml.py
LATSourceModel/model_components.py
LATSourceModel/utilities.py
LATSourceModel-1.10.11.dist-info/LICENSE
LATSourceModel-1.10.11.dist-info/METADATA
LATSourceModel-1.10.11.dist-info/WHEEL
LATSourceModel-1.10.11.dist-info/entry_points.txt
LATSourceModel-1.10.11.dist-info/top_level.txt
LATSourceModel-1.10.11.dist-info/RECORD
