Metadata-Version: 2.1
Name: LATSourceModel
Version: 1.10.11
Summary: A set of functions and classes to build spatial-spectral models for analysis of Fermi LAT gamma-ray data.
Author-email: Tyrel Johnson <tyrel.j.johnson@gmail.com>
License: GPL-3.0
Project-URL: Home, https://github.com/physicsranger/make4FGLxml
Project-URL: Issues, https://github.com/physicsranger/make4FGLxml/issues
Classifier: Programming Language :: Python :: 3
Classifier: License :: OSI Approved :: GNU General Public License v3 or later (GPLv3+)
Classifier: Operating System :: OS Independent
Requires-Python: >=3.4
License-File: LICENSE
Requires-Dist: numpy
Requires-Dist: pandas
Requires-Dist: astropy
